Metadata-Version: 2.1
Name: import-serial
Version: 0.5
Summary: Import diffractio data from serial macromolecular crystallography
Home-page: https://www.ccp4.ac.uk/
Author: Martin Maly
Author-email: martin.maly@soton.ac.uk
License: GNU Lesser General Public License v3 (LGPLv3)
Keywords: macromolecular crystallography,research
Classifier: Environment :: Console
Classifier: Environment :: Web Environment
Classifier: Intended Audience :: Science/Research
Classifier: License :: OSI Approved :: GNU Lesser General Public License v3 (LGPLv3)
Classifier: Natural Language :: English
Classifier: Operating System :: POSIX :: Linux
Classifier: Operating System :: Microsoft :: Windows
Classifier: Operating System :: MacOS
Classifier: Programming Language :: Python
Classifier: Programming Language :: Python :: 3
Classifier: Topic :: Scientific/Engineering :: Bio-Informatics
Classifier: Topic :: Scientific/Engineering :: Physics
License-File: LICENSE
